README.md
setup.cfg
setup.py
keras_wrn/__init__.py
keras_wrn/wrn.py
keras_wrn.egg-info/PKG-INFO
keras_wrn.egg-info/SOURCES.txt
keras_wrn.egg-info/dependency_links.txt
keras_wrn.egg-info/not-zip-safe
keras_wrn.egg-info/requires.txt
keras_wrn.egg-info/top_level.txt