Metadata-Version: 1.0
Name: keras-wrn
Version: 0.2
Summary: The Keras package for Wide Residual Networks
Home-page: https://github.com/EricAlcaide/keras-wrn
Author: Eric Alcaide
Author-email: ericalcaide1@gmail.com
License: MIT
Platform: UNKNOWN
